twitchio/__init__.py
twitchio/__main__.py
twitchio/assets.py
twitchio/backoff.py
twitchio/client.py
twitchio/events.pyi
twitchio/exceptions.py
twitchio/http.py
twitchio/payloads.py
twitchio/py.typed
twitchio/user.py
twitchio/utils.py
twitchio/authentication/__init__.py
twitchio/authentication/oauth.py
twitchio/authentication/payloads.py
twitchio/authentication/scopes.py
twitchio/authentication/tokens.py
twitchio/eventsub/__init__.py
twitchio/eventsub/enums.py
twitchio/eventsub/subscriptions.py
twitchio/eventsub/websockets.py
twitchio/ext/commands/__init__.py
twitchio/ext/commands/bot.py
twitchio/ext/commands/components.py
twitchio/ext/commands/context.py
twitchio/ext/commands/converters.py
twitchio/ext/commands/cooldowns.py
twitchio/ext/commands/core.py
twitchio/ext/commands/exceptions.py
twitchio/ext/commands/py.typed
twitchio/ext/commands/translators.py
twitchio/ext/commands/types_.py
twitchio/ext/commands/view.py
twitchio/ext/routines/__init__.py
twitchio/models/__init__.py
twitchio/models/ads.py
twitchio/models/analytics.py
twitchio/models/bits.py
twitchio/models/ccls.py
twitchio/models/channel_points.py
twitchio/models/channels.py
twitchio/models/charity.py
twitchio/models/chat.py
twitchio/models/clips.py
twitchio/models/entitlements.py
twitchio/models/eventsub_.py
twitchio/models/games.py
twitchio/models/goals.py
twitchio/models/guest_star.py
twitchio/models/hype_train.py
twitchio/models/moderation.py
twitchio/models/polls.py
twitchio/models/predictions.py
twitchio/models/raids.py
twitchio/models/schedule.py
twitchio/models/search.py
twitchio/models/streams.py
twitchio/models/subscriptions.py
twitchio/models/teams.py
twitchio/models/videos.py
twitchio/types_/__init__.py
twitchio/types_/colours.py
twitchio/types_/conduits.py
twitchio/types_/eventsub.py
twitchio/types_/options.py
twitchio/types_/requests.py
twitchio/types_/responses.py
twitchio/types_/tokens.py
twitchio/web/__init__.py
twitchio/web/aio_adapter.py
twitchio/web/starlette_adapter.py
twitchio-3.2.1.dist-info/licenses/LICENSE
twitchio-3.2.1.dist-info/METADATA
twitchio-3.2.1.dist-info/WHEEL
twitchio-3.2.1.dist-info/top_level.txt
twitchio-3.2.1.dist-info/RECORD
