Metadata-Version: 2.4
Name: twitchio
Version: 3.2.1
Summary: A powerful, asynchronous Python library for twitch.tv.
Author: PythonistaGuild
Project-URL: Homepage, https://github.com/PythonistaGuild/TwitchIO
Project-URL: Documentation, https://twitchio.dev
Project-URL: Issue tracker, https://github.com/PythonistaGuild/TwitchIO/issues
Classifier: License :: OSI Approved :: MIT License
Classifier: Intended Audience :: Developers
Classifier: Natural Language :: English
Classifier: Operating System :: OS Independent
Classifier: Programming Language :: Python :: 3.11
Classifier: Programming Language :: Python :: 3.12
Classifier: Programming Language :: Python :: 3.13
Classifier: Topic :: Internet
Classifier: Topic :: Software Development :: Libraries
Classifier: Topic :: Software Development :: Libraries :: Python Modules
Classifier: Topic :: Utilities
Requires-Python: >=3.11
License-File: LICENSE
Requires-Dist: aiohttp<4,>=3.9.1
Provides-Extra: docs
Requires-Dist: sphinx-wagtail-theme; extra == "docs"
Requires-Dist: sphinx; extra == "docs"
Requires-Dist: docutils<0.18; extra == "docs"
Requires-Dist: sphinxcontrib-napoleon; extra == "docs"
Requires-Dist: sphinxcontrib-asyncio; extra == "docs"
Requires-Dist: sphinxcontrib-websupport; extra == "docs"
Requires-Dist: Pygments; extra == "docs"
Requires-Dist: sphinx-hoverxref; extra == "docs"
Requires-Dist: sphinxcontrib_trio; extra == "docs"
Provides-Extra: starlette
Requires-Dist: starlette; extra == "starlette"
Requires-Dist: uvicorn; extra == "starlette"
Provides-Extra: dev
Requires-Dist: ruff==0.11.2; extra == "dev"
Requires-Dist: pyright==1.1.402; extra == "dev"
Requires-Dist: isort; extra == "dev"
Dynamic: license-file
